<?xml version = '1.0' encoding = 'UTF-8'?>
<FKIndexAssociation class="oracle.dbtools.crest.model.design.relational.FKIndexAssociation" id="2500E15A-118C-1B59-2F79-59D1C8F15999" directorySegmentName="seg_0" name="subdiv_school_district_rel">
<createdBy>Katarina</createdBy>
<createdTime>2013-11-26 23:56:28 UTC</createdTime>
<generatorID>9C45759C-4148-A996-123C-B04E92BAF9D7</generatorID>
<ownerDesignName>eggshell_model</ownerDesignName>
<containerWithKeyObject>06089130-2B7D-4CFF-A225-59E26E9FC36D</containerWithKeyObject>
<deleteRule>RESTRICT</deleteRule>
<localFKIndex>3F3DE08A-F8BC-2674-5F53-FE2F230FDA06</localFKIndex>
<keyObject>5E1D2999-0BB6-C3AF-20AB-5E8600B2CA61</keyObject>
<mandatory>true</mandatory>
<transferable>true</transferable>
</FKIndexAssociation>