<?xml version = '1.0' encoding = 'UTF-8'?>
<FKIndexAssociation class="oracle.dbtools.crest.model.design.relational.FKIndexAssociation" id="D4A27A03-C40B-7B99-A05B-E5544B05342A" directorySegmentName="seg_0" name="house_contract">
<createdBy>Katarina</createdBy>
<createdTime>2013-11-26 17:31:49 UTC</createdTime>
<generatorID>07692E7D-3842-D480-8F35-4337D3F87850</generatorID>
<ownerDesignName>eggshell_model</ownerDesignName>
<containerWithKeyObject>22F8F108-AB2F-31B6-AF18-1A041E735E07</containerWithKeyObject>
<deleteRule>RESTRICT</deleteRule>
<localFKIndex>7418F9D6-7ACA-D26E-5D3E-AB60AFC674B9</localFKIndex>
<keyObject>52F5C3B4-B900-02A2-4EB6-43AA6CCD182D</keyObject>
<mandatory>true</mandatory>
<transferable>true</transferable>
</FKIndexAssociation>