<?xml version = '1.0' encoding = 'UTF-8'?>
<FKIndexAssociation class="oracle.dbtools.crest.model.design.relational.FKIndexAssociation" id="C7B3FE3B-7BC5-CFEF-7473-B92EA8FCCF57" directorySegmentName="seg_0" name="Style_elevation_rel">
<createdBy>Katarina</createdBy>
<createdTime>2013-11-21 00:22:42 UTC</createdTime>
<generatorID>26C026AB-A3FF-25BE-0AAF-D328A4108DCE</generatorID>
<ownerDesignName>eggshell_model</ownerDesignName>
<containerWithKeyObject>78B12CDB-BCDD-1372-8DBB-E3E2197BB12E</containerWithKeyObject>
<deleteRule>RESTRICT</deleteRule>
<localFKIndex>F22232B3-8F93-9476-24AE-AC5B59C9BEA4</localFKIndex>
<keyObject>F7306876-31F6-AC55-0724-47FFE4E0FD89</keyObject>
<mandatory>true</mandatory>
<transferable>true</transferable>
</FKIndexAssociation>