<?xml version = '1.0' encoding = 'UTF-8'?>
<Table class="oracle.dbtools.crest.model.design.relational.Table" id="F20F5DBB-2AF2-EBFE-243F-355391019A1B" directorySegmentName="seg_0" name="Sales_agent_assignment">
<createdBy>Katarina</createdBy>
<createdTime>2013-11-26 21:16:20 UTC</createdTime>
<generatorID>4990A0FC-C0F3-71CE-D3E5-A7EDF6ECDE10</generatorID>
<ownerDesignName>eggshell_model</ownerDesignName>
<pkName>Sales_agent_assignment_PK</pkName>
<fonts>
<FontObject class="oracle.dbtools.crest.model.design.FontObjectWr">
<foType>Title</foType>
<fontStyle>1</fontStyle>
<colorRGB>-16776961</colorRGB>
</FontObject>
<FontObject class="oracle.dbtools.crest.model.design.FontObjectWr">
<foType>Column</foType>
<colorRGB>-16777216</colorRGB>
</FontObject>
<FontObject class="oracle.dbtools.crest.model.design.FontObjectWr">
<foType>Datatype</foType>
<colorRGB>-16744448</colorRGB>
</FontObject>
<FontObject class="oracle.dbtools.crest.model.design.FontObjectWr">
<foType>PK Element</foType>
<colorRGB>-16776961</colorRGB>
</FontObject>
<FontObject class="oracle.dbtools.crest.model.design.FontObjectWr">
<foType>FK Element</foType>
<colorRGB>-16777216</colorRGB>
</FontObject>
<FontObject class="oracle.dbtools.crest.model.design.FontObjectWr">
<foType>UK Element</foType>
<colorRGB>-16776961</colorRGB>
</FontObject>
<FontObject class="oracle.dbtools.crest.model.design.FontObjectWr">
<foType>Not Null</foType>
<colorRGB>-65536</colorRGB>
</FontObject>
<FontObject class="oracle.dbtools.crest.model.design.FontObjectWr">
<foType>Key</foType>
<colorRGB>-16777216</colorRGB>
</FontObject>
</fonts>
<columns>
<Column class="oracle.dbtools.crest.model.design.relational.Column" name="sales_agent_assignment_id" id="70FC23C8-6D3E-75A3-DA46-03EFE3547377">
<createdBy>Katarina</createdBy>
<createdTime>2013-11-26 21:16:20 UTC</createdTime>
<generatorID>F0821045-6D2E-A88C-FE03-973A3CD7421F</generatorID>
<ownerDesignName>eggshell_model</ownerDesignName>
<useDomainConstraints>false</useDomainConstraints>
<use>1</use>
<logicalDatatype>LOGDT019</logicalDatatype>
<previousColumn>false</previousColumn>
<autoIncrementCycle>false</autoIncrementCycle>
</Column>
<Column class="oracle.dbtools.crest.model.design.relational.Column" name="house_id" id="E6371E19-18AD-9F43-970F-EFF732FED19C">
<createdBy>Katarina</createdBy>
<createdTime>2013-11-26 21:16:28 UTC</createdTime>
<generatorID>B2EE9E3A-E98E-4C5F-A3A5-91B936778DEE</generatorID>
<ownerDesignName>eggshell_model</ownerDesignName>
<use>1</use>
<logicalDatatype>LOGDT019</logicalDatatype>
<delegate>B16AA6FC-A380-9610-F06D-BC88BC912A63</delegate>
<previousColumn>false</previousColumn>
<autoIncrementCycle>false</autoIncrementCycle>
<associations>
<colAssociation fkAssociation="862CE229-297B-3CB2-83FC-AD4E5ABCBCB2" referredColumn="B16AA6FC-A380-9610-F06D-BC88BC912A63"/>
</associations>
</Column>
<Column class="oracle.dbtools.crest.model.design.relational.Column" name="sales_agent_id" id="69E71C34-8432-CD91-C5FB-4B5BA0D2F3DC">
<createdBy>Katarina</createdBy>
<createdTime>2013-11-26 21:16:28 UTC</createdTime>
<generatorID>19D33C59-D2CE-B20F-B58B-4C7AD6BE02D5</generatorID>
<ownerDesignName>eggshell_model</ownerDesignName>
<use>1</use>
<logicalDatatype>LOGDT019</logicalDatatype>
<delegate>78851DBE-74B0-943D-E048-0AF8639D62CC</delegate>
<previousColumn>false</previousColumn>
<autoIncrementCycle>false</autoIncrementCycle>
<associations>
<colAssociation fkAssociation="FAA89F5F-1CBE-A343-068D-54DB8B3D11DC" referredColumn="78851DBE-74B0-943D-E048-0AF8639D62CC"/>
</associations>
</Column>
<Column class="oracle.dbtools.crest.model.design.relational.Column" name="start_date" id="B91DF97A-E620-04C1-638D-5BD779DCBE02">
<createdBy>Katarina</createdBy>
<createdTime>2013-11-26 21:16:20 UTC</createdTime>
<generatorID>3B5DDF5B-B791-37B4-EA38-B683EEEE2457</generatorID>
<ownerDesignName>eggshell_model</ownerDesignName>
<useDomainConstraints>false</useDomainConstraints>
<use>1</use>
<logicalDatatype>LOGDT008</logicalDatatype>
<previousColumn>false</previousColumn>
<autoIncrementCycle>false</autoIncrementCycle>
</Column>
<Column class="oracle.dbtools.crest.model.design.relational.Column" name="end_date" id="4E5F0829-EE62-ECAE-FE22-C7F469EE369D">
<createdBy>Katarina</createdBy>
<createdTime>2013-11-26 21:16:20 UTC</createdTime>
<generatorID>CF3CB811-B4CB-B757-3FEF-B7B4DBD9B4A5</generatorID>
<ownerDesignName>eggshell_model</ownerDesignName>
<nullsAllowed>true</nullsAllowed>
<useDomainConstraints>false</useDomainConstraints>
<use>1</use>
<logicalDatatype>LOGDT008</logicalDatatype>
<previousColumn>false</previousColumn>
<autoIncrementCycle>false</autoIncrementCycle>
</Column>
<Column class="oracle.dbtools.crest.model.design.relational.Column" name="is_main_sales_agent" id="82FAD8C6-3D11-B4CC-F295-F79FC4B186CB">
<createdBy>Katarina</createdBy>
<createdTime>2013-11-26 21:16:20 UTC</createdTime>
<generatorID>6D7E7E9A-9557-881A-28DC-17BFA153196C</generatorID>
<ownerDesignName>eggshell_model</ownerDesignName>
<useDomainConstraints>false</useDomainConstraints>
<defaultValue>false</defaultValue>
<use>1</use>
<logicalDatatype>LOGDT006</logicalDatatype>
<previousColumn>false</previousColumn>
<autoIncrementCycle>false</autoIncrementCycle>
</Column>
</columns>
<indexes>
<ind_PK_UK class="oracle.dbtools.crest.model.design.relational.Index" id="4ABF5435-4B7C-7D6A-4D2C-40676F669DFA" name="Sales_agent_assignment_PK">
<createdBy>Katarina</createdBy>
<createdTime>2013-11-26 21:16:20 UTC</createdTime>
<generatorID>5485A72D-F698-7E3F-B0A5-79E8519D6A10</generatorID>
<ownerDesignName>eggshell_model</ownerDesignName>
<pk>true</pk>
<indexState>Primary Constraint</indexState>
<indexColumnUsage>
<colUsage columnID="70FC23C8-6D3E-75A3-DA46-03EFE3547377"/>
</indexColumnUsage>
</ind_PK_UK>
<ind_PK_UK class="oracle.dbtools.crest.model.design.relational.Index" id="EA32232A-94DD-1A91-464A-5C0F55CEF11C" name="house_sales_agent_assign_rel">
<createdBy>Katarina</createdBy>
<createdTime>2013-11-26 21:16:20 UTC</createdTime>
<generatorID>8A7D147D-4F02-1969-3294-D3039B22D592</generatorID>
<ownerDesignName>eggshell_model</ownerDesignName>
<indexState>Foreign Key</indexState>
<indexColumnUsage>
<colUsage columnID="E6371E19-18AD-9F43-970F-EFF732FED19C"/>
</indexColumnUsage>
</ind_PK_UK>
<ind_PK_UK class="oracle.dbtools.crest.model.design.relational.Index" id="22556A93-BD1D-730A-1795-3C894F16CC5C" name="sales_agent_assignment_rel">
<createdBy>Katarina</createdBy>
<createdTime>2013-11-26 21:16:20 UTC</createdTime>
<generatorID>749991F0-6E93-90C6-1C2E-2F960600A903</generatorID>
<ownerDesignName>eggshell_model</ownerDesignName>
<indexState>Foreign Key</indexState>
<indexColumnUsage>
<colUsage columnID="69E71C34-8432-CD91-C5FB-4B5BA0D2F3DC"/>
</indexColumnUsage>
</ind_PK_UK>
</indexes>
</Table>