<?xml version = '1.0' encoding = 'UTF-8'?>
<FKIndexAssociation class="oracle.dbtools.crest.model.design.relational.FKIndexAssociation" id="62BF586F-B793-D0D3-DEE2-3B99229DE6D5" directorySegmentName="seg_0" name="reversed_style">
<createdBy>Katarina</createdBy>
<createdTime>2013-11-17 17:15:14 UTC</createdTime>
<generatorID>1E8541A6-DE13-F86E-9545-4290B8512EC4</generatorID>
<ownerDesignName>eggshell_model</ownerDesignName>
<containerWithKeyObject>3A12927A-5DE6-2611-B95E-75A40AD30C5B</containerWithKeyObject>
<deleteRule>RESTRICT</deleteRule>
<localFKIndex>2739DB0D-2DB6-BAB2-8573-DF6D13992805</localFKIndex>
<keyObject>69BCF199-7696-5513-B1C9-BEDF3DD2D36B</keyObject>
<mandatory>false</mandatory>
<transferable>true</transferable>
</FKIndexAssociation>