<?xml version = '1.0' encoding = 'UTF-8'?>
<Table class="oracle.dbtools.crest.model.design.relational.Table" id="89055C0A-378D-C679-5D68-E613401E43A7" directorySegmentName="seg_0" name="Subdivision_agreement_assignment">
<createdBy>Katarina</createdBy>
<createdTime>2013-11-17 01:43:15 UTC</createdTime>
<generatorID>89FF3AD2-E27A-F4C4-89B5-D2DDF555DF62</generatorID>
<ownerDesignName>eggshell_model</ownerDesignName>
<pkName>Subdivision_agreement_assignment_PK</pkName>
<fonts>
<FontObject class="oracle.dbtools.crest.model.design.FontObjectWr">
<foType>Title</foType>
<fontStyle>1</fontStyle>
<colorRGB>-16776961</colorRGB>
</FontObject>
<FontObject class="oracle.dbtools.crest.model.design.FontObjectWr">
<foType>Column</foType>
<colorRGB>-16777216</colorRGB>
</FontObject>
<FontObject class="oracle.dbtools.crest.model.design.FontObjectWr">
<foType>Datatype</foType>
<colorRGB>-16744448</colorRGB>
</FontObject>
<FontObject class="oracle.dbtools.crest.model.design.FontObjectWr">
<foType>PK Element</foType>
<colorRGB>-16776961</colorRGB>
</FontObject>
<FontObject class="oracle.dbtools.crest.model.design.FontObjectWr">
<foType>FK Element</foType>
<colorRGB>-16777216</colorRGB>
</FontObject>
<FontObject class="oracle.dbtools.crest.model.design.FontObjectWr">
<foType>UK Element</foType>
<colorRGB>-16776961</colorRGB>
</FontObject>
<FontObject class="oracle.dbtools.crest.model.design.FontObjectWr">
<foType>Not Null</foType>
<colorRGB>-65536</colorRGB>
</FontObject>
<FontObject class="oracle.dbtools.crest.model.design.FontObjectWr">
<foType>Key</foType>
<colorRGB>-16777216</colorRGB>
</FontObject>
</fonts>
<columns>
<Column class="oracle.dbtools.crest.model.design.relational.Column" name="subdivison_agreement_assignment_id" id="64035D58-AF9B-BC81-A55B-44229D6D3137">
<createdBy>Katarina</createdBy>
<createdTime>2013-11-17 01:43:15 UTC</createdTime>
<generatorID>8F62AB3F-D304-C595-7623-A4EAFFF776FA</generatorID>
<ownerDesignName>eggshell_model</ownerDesignName>
<use>0</use>
<logicalDatatype>LOGDT019</logicalDatatype>
<domain>1C83044F-F4AD-B495-5726-6FF2A6D331C5</domain>
<previousColumn>false</previousColumn>
<autoIncrementCycle>false</autoIncrementCycle>
</Column>
<Column class="oracle.dbtools.crest.model.design.relational.Column" name="subdivision_agreement_id" id="B23FC75C-0266-993F-65C7-293B2C9095DD">
<createdBy>Katarina</createdBy>
<createdTime>2013-11-17 01:43:15 UTC</createdTime>
<generatorID>5161602F-F4F6-73E7-2509-76FEE1EA458D</generatorID>
<ownerDesignName>eggshell_model</ownerDesignName>
<nullsAllowed>true</nullsAllowed>
<use>0</use>
<logicalDatatype>LOGDT019</logicalDatatype>
<domain>1C83044F-F4AD-B495-5726-6FF2A6D331C5</domain>
<delegate>E2474A3F-A5B5-F495-BA80-1DD0A9BDDECC</delegate>
<previousColumn>false</previousColumn>
<autoIncrementCycle>false</autoIncrementCycle>
<associations>
<colAssociation fkAssociation="9EB2BE66-7B7D-3544-1D87-A9D1E4FE5A68" referredColumn="E2474A3F-A5B5-F495-BA80-1DD0A9BDDECC"/>
</associations>
</Column>
<Column class="oracle.dbtools.crest.model.design.relational.Column" name="date_submitted" id="CF0FCA8F-DBE3-9603-680C-BCB9DFC24E24">
<createdBy>Katarina</createdBy>
<createdTime>2013-11-17 01:43:15 UTC</createdTime>
<generatorID>C5226E9B-E6DD-599A-0B0D-37B184B4509D</generatorID>
<ownerDesignName>eggshell_model</ownerDesignName>
<nullsAllowed>true</nullsAllowed>
<use>0</use>
<logicalDatatype>LOGDT008</logicalDatatype>
<domain>2FF7B1E7-B0D4-FE14-1A61-196E6487640C</domain>
<previousColumn>false</previousColumn>
<autoIncrementCycle>false</autoIncrementCycle>
</Column>
<Column class="oracle.dbtools.crest.model.design.relational.Column" name="scanned_image" id="081E9476-F8F1-2561-57B9-FB7B7947293F">
<createdBy>Katarina</createdBy>
<createdTime>2013-11-17 01:43:15 UTC</createdTime>
<generatorID>ED5AF12F-D462-E982-601C-F5CEA0784A87</generatorID>
<ownerDesignName>eggshell_model</ownerDesignName>
<nullsAllowed>true</nullsAllowed>
<use>0</use>
<logicalDatatype>LOGDT010</logicalDatatype>
<domain>EE30804D-DECE-2382-CA51-7E87EA989C3F</domain>
<previousColumn>false</previousColumn>
<autoIncrementCycle>false</autoIncrementCycle>
</Column>
</columns>
<indexes>
<ind_PK_UK class="oracle.dbtools.crest.model.design.relational.Index" id="228BF777-A014-BD6F-7455-D572F288B65F" name="Subdivision_agreement_assignment_PK">
<createdBy>Katarina</createdBy>
<createdTime>2013-11-17 01:43:15 UTC</createdTime>
<generatorID>ACB27B0A-3E74-F1A9-9914-8075D466D874</generatorID>
<ownerDesignName>eggshell_model</ownerDesignName>
<pk>true</pk>
<indexState>Primary Constraint</indexState>
<indexColumnUsage>
<colUsage columnID="64035D58-AF9B-BC81-A55B-44229D6D3137"/>
</indexColumnUsage>
</ind_PK_UK>
<ind_PK_UK class="oracle.dbtools.crest.model.design.relational.Index" id="5171B1D8-92BA-16CD-D253-44D9E90FD8C5" name="subdivison_agreement_assignment_rel">
<createdBy>Katarina</createdBy>
<createdTime>2013-11-17 01:43:15 UTC</createdTime>
<generatorID>A7EFBA34-0636-3E0F-35F5-4DC31882D23F</generatorID>
<ownerDesignName>eggshell_model</ownerDesignName>
<indexState>Foreign Key</indexState>
<indexColumnUsage>
<colUsage columnID="B23FC75C-0266-993F-65C7-293B2C9095DD"/>
</indexColumnUsage>
</ind_PK_UK>
</indexes>
</Table>