<?xml version = '1.0' encoding = 'UTF-8'?>
<Table class="oracle.dbtools.crest.model.design.relational.Table" id="AEF6F155-A0B4-1271-BA0E-BAB494210279" directorySegmentName="seg_0" name="Lot">
<createdBy>Katarina</createdBy>
<createdTime>2013-11-11 02:46:01 UTC</createdTime>
<generatorID>D104F706-AE39-0576-598B-65D202EE4E63</generatorID>
<ownerDesignName>eggshell_model</ownerDesignName>
<pkName>Lot PK</pkName>
<fonts>
<FontObject class="oracle.dbtools.crest.model.design.FontObjectWr">
<foType>Title</foType>
<fontStyle>1</fontStyle>
<colorRGB>-16776961</colorRGB>
</FontObject>
<FontObject class="oracle.dbtools.crest.model.design.FontObjectWr">
<foType>Column</foType>
<colorRGB>-16777216</colorRGB>
</FontObject>
<FontObject class="oracle.dbtools.crest.model.design.FontObjectWr">
<foType>Datatype</foType>
<colorRGB>-16744448</colorRGB>
</FontObject>
<FontObject class="oracle.dbtools.crest.model.design.FontObjectWr">
<foType>PK Element</foType>
<colorRGB>-16776961</colorRGB>
</FontObject>
<FontObject class="oracle.dbtools.crest.model.design.FontObjectWr">
<foType>FK Element</foType>
<colorRGB>-16777216</colorRGB>
</FontObject>
<FontObject class="oracle.dbtools.crest.model.design.FontObjectWr">
<foType>UK Element</foType>
<colorRGB>-16776961</colorRGB>
</FontObject>
<FontObject class="oracle.dbtools.crest.model.design.FontObjectWr">
<foType>Not Null</foType>
<colorRGB>-65536</colorRGB>
</FontObject>
<FontObject class="oracle.dbtools.crest.model.design.FontObjectWr">
<foType>Key</foType>
<colorRGB>-16777216</colorRGB>
</FontObject>
</fonts>
<columns>
<Column class="oracle.dbtools.crest.model.design.relational.Column" name="lot_id" id="DB41AFCE-FDBC-1B87-8589-09746EDFE1B8">
<createdBy>Katarina</createdBy>
<createdTime>2013-11-11 02:46:01 UTC</createdTime>
<generatorID>BF19ABDB-361B-5D12-5CA2-4851BACE3159</generatorID>
<ownerDesignName>eggshell_model</ownerDesignName>
<use>0</use>
<logicalDatatype>LOGDT019</logicalDatatype>
<domain>1C83044F-F4AD-B495-5726-6FF2A6D331C5</domain>
<previousColumn>false</previousColumn>
<autoIncrementCycle>false</autoIncrementCycle>
</Column>
<Column class="oracle.dbtools.crest.model.design.relational.Column" name="latitude" id="D0909E79-F7D3-3442-3774-760F972AD59A">
<createdBy>Katarina</createdBy>
<createdTime>2013-11-11 02:46:01 UTC</createdTime>
<generatorID>6EF28FC5-8A7A-FD44-5686-3D218950A7B7</generatorID>
<ownerDesignName>eggshell_model</ownerDesignName>
<nullsAllowed>true</nullsAllowed>
<use>0</use>
<logicalDatatype>LOGDT026</logicalDatatype>
<domain>4BCCE704-B58C-501E-940C-C630A7B16250</domain>
<previousColumn>false</previousColumn>
<autoIncrementCycle>false</autoIncrementCycle>
</Column>
<Column class="oracle.dbtools.crest.model.design.relational.Column" name="longitude" id="97483658-1368-70C2-C35E-C78A60E23C4A">
<createdBy>Katarina</createdBy>
<createdTime>2013-11-11 02:46:01 UTC</createdTime>
<generatorID>FECE25F5-99B5-4CC5-FBA3-C4112EFFD544</generatorID>
<ownerDesignName>eggshell_model</ownerDesignName>
<nullsAllowed>true</nullsAllowed>
<use>0</use>
<logicalDatatype>LOGDT026</logicalDatatype>
<domain>4BCCE704-B58C-501E-940C-C630A7B16250</domain>
<previousColumn>false</previousColumn>
<autoIncrementCycle>false</autoIncrementCycle>
</Column>
<Column class="oracle.dbtools.crest.model.design.relational.Column" name="house_id" id="0EDF7561-C0A6-4283-97AD-64E7C7316072">
<createdBy>Katarina</createdBy>
<createdTime>2013-11-11 02:46:01 UTC</createdTime>
<generatorID>8B678E08-DE9B-2DA6-F05F-BDAAEFC450CC</generatorID>
<ownerDesignName>eggshell_model</ownerDesignName>
<use>0</use>
<logicalDatatype>LOGDT019</logicalDatatype>
<domain>1C83044F-F4AD-B495-5726-6FF2A6D331C5</domain>
<delegate>477421AD-A93D-EAD2-B400-602BBE69C688</delegate>
<previousColumn>false</previousColumn>
<autoIncrementCycle>false</autoIncrementCycle>
<associations>
<colAssociation fkAssociation="42EE0A9F-FB34-BBFC-5FB7-2FAF19FBFC2D" referredColumn="477421AD-A93D-EAD2-B400-602BBE69C688"/>
</associations>
</Column>
<Column class="oracle.dbtools.crest.model.design.relational.Column" name="subdivision_id" id="1A7D20BF-A9A3-7925-92D5-A0C71A9DDFA9">
<createdBy>Katarina</createdBy>
<createdTime>2013-11-11 02:46:01 UTC</createdTime>
<generatorID>3D6ED76F-E996-E06E-4D84-C8463D7AAFAE</generatorID>
<ownerDesignName>eggshell_model</ownerDesignName>
<nullsAllowed>true</nullsAllowed>
<use>0</use>
<logicalDatatype>LOGDT019</logicalDatatype>
<domain>1C83044F-F4AD-B495-5726-6FF2A6D331C5</domain>
<delegate>B5897AE0-6536-93FF-6153-4C49F912FDFF</delegate>
<previousColumn>false</previousColumn>
<autoIncrementCycle>false</autoIncrementCycle>
<associations>
<colAssociation fkAssociation="DCB65123-5576-B385-B099-30B4253740CF" referredColumn="B5897AE0-6536-93FF-6153-4C49F912FDFF"/>
</associations>
</Column>
<Column class="oracle.dbtools.crest.model.design.relational.Column" name="style_elevation_id" id="3D273F35-B400-4106-7AC8-D8D32E756D42">
<createdBy>Katarina</createdBy>
<createdTime>2013-11-11 16:14:18 UTC</createdTime>
<generatorID>5B7E9EF3-0379-159C-FCD9-2BF658B1130C</generatorID>
<ownerDesignName>eggshell_model</ownerDesignName>
<nullsAllowed>true</nullsAllowed>
<use>0</use>
<logicalDatatype>LOGDT019</logicalDatatype>
<domain>1C83044F-F4AD-B495-5726-6FF2A6D331C5</domain>
<delegate>86573E77-C46E-7150-6C00-23488381FDB4</delegate>
<previousColumn>false</previousColumn>
<autoIncrementCycle>false</autoIncrementCycle>
<associations>
<colAssociation fkAssociation="C0743DED-11AC-87D4-09B3-12959FCF52EE" referredColumn="86573E77-C46E-7150-6C00-23488381FDB4"/>
</associations>
</Column>
</columns>
<indexes>
<ind_PK_UK class="oracle.dbtools.crest.model.design.relational.Index" id="77090968-DAFA-3645-7676-C4B83935D639" name="Lot PK">
<createdBy>Katarina</createdBy>
<createdTime>2013-11-11 02:46:01 UTC</createdTime>
<generatorID>3BAE1301-3D41-364D-C101-7BB35F153B98</generatorID>
<ownerDesignName>eggshell_model</ownerDesignName>
<pk>true</pk>
<indexState>Primary Constraint</indexState>
<indexColumnUsage>
<colUsage columnID="DB41AFCE-FDBC-1B87-8589-09746EDFE1B8"/>
</indexColumnUsage>
</ind_PK_UK>
<ind_PK_UK class="oracle.dbtools.crest.model.design.relational.Index" id="186B7A25-AAA3-C565-1CBF-3D6382183CD1" name="Lot__IDX">
<createdBy>Katarina</createdBy>
<createdTime>2013-11-11 02:46:01 UTC</createdTime>
<ownerDesignName>eggshell_model</ownerDesignName>
<indexState>Unique Plain Index</indexState>
<indexColumnUsage>
<colUsage columnID="0EDF7561-C0A6-4283-97AD-64E7C7316072"/>
</indexColumnUsage>
</ind_PK_UK>
<ind_PK_UK class="oracle.dbtools.crest.model.design.relational.Index" id="2F528B9F-5680-3B3F-701E-5C3A776632D4" name="House_lot_rel">
<createdBy>Katarina</createdBy>
<createdTime>2013-11-11 02:46:01 UTC</createdTime>
<generatorID>F038AFE9-97EF-0B5B-5602-98DC6B54F7F2</generatorID>
<ownerDesignName>eggshell_model</ownerDesignName>
<indexState>Foreign Key</indexState>
<indexColumnUsage>
<colUsage columnID="0EDF7561-C0A6-4283-97AD-64E7C7316072"/>
</indexColumnUsage>
</ind_PK_UK>
<ind_PK_UK class="oracle.dbtools.crest.model.design.relational.Index" id="91EAAD59-BFCF-CAE3-CB0E-B2F7FE492C3F" name="Subdivision_lot_rel">
<createdBy>Katarina</createdBy>
<createdTime>2013-11-11 02:46:01 UTC</createdTime>
<generatorID>CF6C2B45-460C-05A5-5911-D0A896B85561</generatorID>
<ownerDesignName>eggshell_model</ownerDesignName>
<indexState>Foreign Key</indexState>
<indexColumnUsage>
<colUsage columnID="1A7D20BF-A9A3-7925-92D5-A0C71A9DDFA9"/>
</indexColumnUsage>
</ind_PK_UK>
<ind_PK_UK class="oracle.dbtools.crest.model.design.relational.Index" id="E36CD638-6805-CD7A-9424-0CDFC823608E" name="Lot_style_elevation">
<createdBy>Katarina</createdBy>
<createdTime>2013-11-11 16:14:18 UTC</createdTime>
<generatorID>36D41AAF-22BE-A748-43C9-1386F44D93FB</generatorID>
<ownerDesignName>eggshell_model</ownerDesignName>
<indexState>Foreign Key</indexState>
<indexColumnUsage>
<colUsage columnID="3D273F35-B400-4106-7AC8-D8D32E756D42"/>
</indexColumnUsage>
</ind_PK_UK>
</indexes>
</Table>