<?xml version = '1.0' encoding = 'UTF-8'?>
<Table class="oracle.dbtools.crest.model.design.relational.Table" id="391C3823-C444-279A-6D84-7BDDD6256B09" directorySegmentName="seg_3" name="STAGE">
<createdBy>Sonal</createdBy>
<createdTime>2013-12-07 20:57:38 UTC</createdTime>
<generatorID>B3AF472D-0E91-B759-27DC-FF7B04952101</generatorID>
<ownerDesignName>Eggshell</ownerDesignName>
<pkName>Stage_PK</pkName>
<fonts>
<FontObject class="oracle.dbtools.crest.model.design.FontObjectWr">
<foType>Title</foType>
<fontStyle>1</fontStyle>
<colorRGB>-16776961</colorRGB>
</FontObject>
<FontObject class="oracle.dbtools.crest.model.design.FontObjectWr">
<foType>Column</foType>
<colorRGB>-16777216</colorRGB>
</FontObject>
<FontObject class="oracle.dbtools.crest.model.design.FontObjectWr">
<foType>Datatype</foType>
<colorRGB>-16744448</colorRGB>
</FontObject>
<FontObject class="oracle.dbtools.crest.model.design.FontObjectWr">
<foType>PK Element</foType>
<colorRGB>-16776961</colorRGB>
</FontObject>
<FontObject class="oracle.dbtools.crest.model.design.FontObjectWr">
<foType>FK Element</foType>
<colorRGB>-16777216</colorRGB>
</FontObject>
<FontObject class="oracle.dbtools.crest.model.design.FontObjectWr">
<foType>UK Element</foType>
<colorRGB>-16776961</colorRGB>
</FontObject>
<FontObject class="oracle.dbtools.crest.model.design.FontObjectWr">
<foType>Not Null</foType>
<colorRGB>-65536</colorRGB>
</FontObject>
<FontObject class="oracle.dbtools.crest.model.design.FontObjectWr">
<foType>Key</foType>
<colorRGB>-16777216</colorRGB>
</FontObject>
</fonts>
<columns>
<Column class="oracle.dbtools.crest.model.design.relational.Column" name="stage_id" id="25C8ABF8-41EC-0889-9BF0-F34D32DA7EC6">
<createdBy>Sonal</createdBy>
<createdTime>2013-12-07 20:57:38 UTC</createdTime>
<generatorID>33A5F160-F5AD-7A43-3721-00C716955222</generatorID>
<ownerDesignName>Eggshell</ownerDesignName>
<use>0</use>
<logicalDatatype>LOGDT019</logicalDatatype>
<domain>1C83044F-F4AD-B495-5726-6FF2A6D331C5</domain>
<previousColumn>false</previousColumn>
<autoIncrementCycle>false</autoIncrementCycle>
</Column>
<Column class="oracle.dbtools.crest.model.design.relational.Column" name="stage_number" id="B8E133BA-E556-1E05-5496-465D64CA4C81">
<createdBy>Sonal</createdBy>
<createdTime>2013-12-07 20:57:38 UTC</createdTime>
<generatorID>DBBDBCE8-356C-84C0-7993-F15EC4BC8B95</generatorID>
<ownerDesignName>Eggshell</ownerDesignName>
<use>0</use>
<logicalDatatype>LOGDT019</logicalDatatype>
<domain>D2545A4D-3262-B77A-2A7C-63A345F86857</domain>
<previousColumn>false</previousColumn>
<autoIncrementCycle>false</autoIncrementCycle>
</Column>
<Column class="oracle.dbtools.crest.model.design.relational.Column" name="description" id="6469C6BC-B3D9-EB1D-FD7D-68FC51C247E0">
<createdBy>Sonal</createdBy>
<createdTime>2013-12-07 20:57:38 UTC</createdTime>
<generatorID>C9C8531B-2A04-AF64-BABB-3D391E7E3C56</generatorID>
<ownerDesignName>Eggshell</ownerDesignName>
<nullsAllowed>true</nullsAllowed>
<use>0</use>
<logicalDatatype>LOGDT024</logicalDatatype>
<domain>7F21DD7B-81C0-047F-A0FF-9FAFE18CB78F</domain>
<previousColumn>false</previousColumn>
<autoIncrementCycle>false</autoIncrementCycle>
</Column>
</columns>
<indexes>
<ind_PK_UK class="oracle.dbtools.crest.model.design.relational.Index" id="05D8554E-86E9-1462-6922-B82E161E03E5" name="Stage_PK">
<createdBy>Sonal</createdBy>
<createdTime>2013-12-07 20:57:38 UTC</createdTime>
<generatorID>5C2D4030-5772-8330-BD04-A82A7A958636</generatorID>
<ownerDesignName>Eggshell</ownerDesignName>
<pk>true</pk>
<indexState>Primary Constraint</indexState>
<indexColumnUsage>
<colUsage columnID="25C8ABF8-41EC-0889-9BF0-F34D32DA7EC6"/>
</indexColumnUsage>
</ind_PK_UK>
</indexes>
</Table>