<?xml version = '1.0' encoding = 'UTF-8'?>
<FKIndexAssociation class="oracle.dbtools.crest.model.design.relational.FKIndexAssociation" id="0EB2839C-47ED-BA60-6D2E-B02664F5A1EC" directorySegmentName="seg_0" name="subdivision_style_rel">
<createdBy>Katarina</createdBy>
<createdTime>2013-11-17 01:43:15 UTC</createdTime>
<generatorID>1EB8AFF9-E1C7-69E4-360B-D87F7F645DE6</generatorID>
<ownerDesignName>eggshell_model</ownerDesignName>
<containerWithKeyObject>77CEF33D-E9B0-8E82-4F6B-3B98545EC765</containerWithKeyObject>
<deleteRule>RESTRICT</deleteRule>
<localFKIndex>BB8ED156-4495-3F09-4B6F-D83B9AB7C5BA</localFKIndex>
<keyObject>41293EB3-D5D1-E2E6-6811-740B167099A5</keyObject>
<mandatory>true</mandatory>
<transferable>true</transferable>
</FKIndexAssociation>