<?xml version = '1.0' encoding = 'UTF-8'?>
<FKIndexAssociation class="oracle.dbtools.crest.model.design.relational.FKIndexAssociation" id="317D099F-F6B0-191E-404A-C4D7C35FC576" directorySegmentName="seg_0" name="reversed_style">
<createdBy>Katarina</createdBy>
<createdTime>2013-11-17 01:43:15 UTC</createdTime>
<generatorID>1E8541A6-DE13-F86E-9545-4290B8512EC4</generatorID>
<ownerDesignName>eggshell_model</ownerDesignName>
<containerWithKeyObject>B37F2B91-5E08-3356-3BAF-42627E5417FA</containerWithKeyObject>
<deleteRule>RESTRICT</deleteRule>
<localFKIndex>B27A8C63-D8A9-DB39-99BD-1D18057E14D3</localFKIndex>
<keyObject>5A109DEA-11A9-F3C9-1E2B-6EE524513046</keyObject>
<mandatory>false</mandatory>
<transferable>true</transferable>
</FKIndexAssociation>