<?xml version = '1.0' encoding = 'UTF-8'?>
<Table class="oracle.dbtools.crest.model.design.relational.Table" id="AF0AC136-FB8A-DAB5-B915-03FC21CC5CDD" directorySegmentName="seg_0" name="Subdiv_agreement_assign">
<createdBy>Katarina</createdBy>
<createdTime>2013-11-17 22:23:30 UTC</createdTime>
<generatorID>89FF3AD2-E27A-F4C4-89B5-D2DDF555DF62</generatorID>
<ownerDesignName>eggshell_model</ownerDesignName>
<pkName>Subdiv_agreement_assign_PK</pkName>
<fonts>
<FontObject class="oracle.dbtools.crest.model.design.FontObjectWr">
<foType>Title</foType>
<fontStyle>1</fontStyle>
<colorRGB>-16776961</colorRGB>
</FontObject>
<FontObject class="oracle.dbtools.crest.model.design.FontObjectWr">
<foType>Column</foType>
<colorRGB>-16777216</colorRGB>
</FontObject>
<FontObject class="oracle.dbtools.crest.model.design.FontObjectWr">
<foType>Datatype</foType>
<colorRGB>-16744448</colorRGB>
</FontObject>
<FontObject class="oracle.dbtools.crest.model.design.FontObjectWr">
<foType>PK Element</foType>
<colorRGB>-16776961</colorRGB>
</FontObject>
<FontObject class="oracle.dbtools.crest.model.design.FontObjectWr">
<foType>FK Element</foType>
<colorRGB>-16777216</colorRGB>
</FontObject>
<FontObject class="oracle.dbtools.crest.model.design.FontObjectWr">
<foType>UK Element</foType>
<colorRGB>-16776961</colorRGB>
</FontObject>
<FontObject class="oracle.dbtools.crest.model.design.FontObjectWr">
<foType>Not Null</foType>
<colorRGB>-65536</colorRGB>
</FontObject>
<FontObject class="oracle.dbtools.crest.model.design.FontObjectWr">
<foType>Key</foType>
<colorRGB>-16777216</colorRGB>
</FontObject>
</fonts>
<columns>
<Column class="oracle.dbtools.crest.model.design.relational.Column" name="subdiv_agreement_assign_id" id="B952CD84-58CF-EDB7-2A77-F627AB4AB9CC">
<createdBy>Katarina</createdBy>
<createdTime>2013-11-17 22:23:30 UTC</createdTime>
<generatorID>8F62AB3F-D304-C595-7623-A4EAFFF776FA</generatorID>
<ownerDesignName>eggshell_model</ownerDesignName>
<use>0</use>
<logicalDatatype>LOGDT019</logicalDatatype>
<domain>1C83044F-F4AD-B495-5726-6FF2A6D331C5</domain>
<previousColumn>false</previousColumn>
<autoIncrementCycle>false</autoIncrementCycle>
</Column>
<Column class="oracle.dbtools.crest.model.design.relational.Column" name="subdivision_agreement_id" id="437E12DD-D6EE-10E4-6874-82B83BE7564C">
<createdBy>Katarina</createdBy>
<createdTime>2013-11-17 22:23:30 UTC</createdTime>
<generatorID>5161602F-F4F6-73E7-2509-76FEE1EA458D</generatorID>
<ownerDesignName>eggshell_model</ownerDesignName>
<use>0</use>
<logicalDatatype>LOGDT019</logicalDatatype>
<domain>1C83044F-F4AD-B495-5726-6FF2A6D331C5</domain>
<delegate>AFA6C034-84C7-1CDE-B414-803AF3C327CA</delegate>
<previousColumn>false</previousColumn>
<autoIncrementCycle>false</autoIncrementCycle>
<associations>
<colAssociation fkAssociation="A1ED1DF7-550A-2222-D09C-5C94251876C5" referredColumn="AFA6C034-84C7-1CDE-B414-803AF3C327CA"/>
</associations>
</Column>
<Column class="oracle.dbtools.crest.model.design.relational.Column" name="date_submitted" id="C69E1399-B3FC-B8BA-3CF8-20F501E40078">
<createdBy>Katarina</createdBy>
<createdTime>2013-11-17 22:23:30 UTC</createdTime>
<generatorID>C5226E9B-E6DD-599A-0B0D-37B184B4509D</generatorID>
<ownerDesignName>eggshell_model</ownerDesignName>
<nullsAllowed>true</nullsAllowed>
<use>0</use>
<logicalDatatype>LOGDT008</logicalDatatype>
<domain>2FF7B1E7-B0D4-FE14-1A61-196E6487640C</domain>
<previousColumn>false</previousColumn>
<autoIncrementCycle>false</autoIncrementCycle>
</Column>
<Column class="oracle.dbtools.crest.model.design.relational.Column" name="scanned_image" id="A226F800-C984-B9EE-50A8-38AD260C533B">
<createdBy>Katarina</createdBy>
<createdTime>2013-11-17 22:23:30 UTC</createdTime>
<generatorID>ED5AF12F-D462-E982-601C-F5CEA0784A87</generatorID>
<ownerDesignName>eggshell_model</ownerDesignName>
<nullsAllowed>true</nullsAllowed>
<use>0</use>
<logicalDatatype>LOGDT010</logicalDatatype>
<domain>EE30804D-DECE-2382-CA51-7E87EA989C3F</domain>
<previousColumn>false</previousColumn>
<autoIncrementCycle>false</autoIncrementCycle>
</Column>
</columns>
<indexes>
<ind_PK_UK class="oracle.dbtools.crest.model.design.relational.Index" id="4F7BEBC4-E7B8-68C6-924C-BE050800FF27" name="Subdiv_agreement_assign_PK">
<createdBy>Katarina</createdBy>
<createdTime>2013-11-17 22:23:30 UTC</createdTime>
<generatorID>ACB27B0A-3E74-F1A9-9914-8075D466D874</generatorID>
<ownerDesignName>eggshell_model</ownerDesignName>
<pk>true</pk>
<indexState>Primary Constraint</indexState>
<indexColumnUsage>
<colUsage columnID="B952CD84-58CF-EDB7-2A77-F627AB4AB9CC"/>
</indexColumnUsage>
</ind_PK_UK>
<ind_PK_UK class="oracle.dbtools.crest.model.design.relational.Index" id="DD612D63-9DC3-CDC1-6E14-833C1CD11A3A" name="subdiv_agreement_assign_rel">
<createdBy>Katarina</createdBy>
<createdTime>2013-11-17 22:23:30 UTC</createdTime>
<generatorID>A7EFBA34-0636-3E0F-35F5-4DC31882D23F</generatorID>
<ownerDesignName>eggshell_model</ownerDesignName>
<indexState>Foreign Key</indexState>
<indexColumnUsage>
<colUsage columnID="437E12DD-D6EE-10E4-6874-82B83BE7564C"/>
</indexColumnUsage>
</ind_PK_UK>
</indexes>
</Table>