<?xml version = '1.0' encoding = 'UTF-8'?>
<Table class="oracle.dbtools.crest.model.design.relational.Table" id="E2F37CAE-9A07-1FD5-3603-4823B2E18978" directorySegmentName="seg_0" name="Customer">
<createdBy>Katarina</createdBy>
<createdTime>2013-11-17 22:23:30 UTC</createdTime>
<generatorID>F3E9DEDF-D625-3315-1A83-BB41CBBFBA6C</generatorID>
<ownerDesignName>eggshell_model</ownerDesignName>
<pkName>Customer_PK</pkName>
<fonts>
<FontObject class="oracle.dbtools.crest.model.design.FontObjectWr">
<foType>Title</foType>
<fontStyle>1</fontStyle>
<colorRGB>-16776961</colorRGB>
</FontObject>
<FontObject class="oracle.dbtools.crest.model.design.FontObjectWr">
<foType>Column</foType>
<colorRGB>-16777216</colorRGB>
</FontObject>
<FontObject class="oracle.dbtools.crest.model.design.FontObjectWr">
<foType>Datatype</foType>
<colorRGB>-16744448</colorRGB>
</FontObject>
<FontObject class="oracle.dbtools.crest.model.design.FontObjectWr">
<foType>PK Element</foType>
<colorRGB>-16776961</colorRGB>
</FontObject>
<FontObject class="oracle.dbtools.crest.model.design.FontObjectWr">
<foType>FK Element</foType>
<colorRGB>-16777216</colorRGB>
</FontObject>
<FontObject class="oracle.dbtools.crest.model.design.FontObjectWr">
<foType>UK Element</foType>
<colorRGB>-16776961</colorRGB>
</FontObject>
<FontObject class="oracle.dbtools.crest.model.design.FontObjectWr">
<foType>Not Null</foType>
<colorRGB>-65536</colorRGB>
</FontObject>
<FontObject class="oracle.dbtools.crest.model.design.FontObjectWr">
<foType>Key</foType>
<colorRGB>-16777216</colorRGB>
</FontObject>
</fonts>
<columns>
<Column class="oracle.dbtools.crest.model.design.relational.Column" name="customer_id" id="B4BBD36B-3BA2-35BC-37F2-BC65DE6134F5">
<createdBy>Katarina</createdBy>
<createdTime>2013-11-17 22:23:30 UTC</createdTime>
<generatorID>37451B39-3BB6-9E85-2FE0-6D6A72AC7617</generatorID>
<ownerDesignName>eggshell_model</ownerDesignName>
<use>0</use>
<logicalDatatype>LOGDT019</logicalDatatype>
<domain>1C83044F-F4AD-B495-5726-6FF2A6D331C5</domain>
<previousColumn>false</previousColumn>
<autoIncrementCycle>false</autoIncrementCycle>
</Column>
<Column class="oracle.dbtools.crest.model.design.relational.Column" name="user_id" id="9B71CDB1-4B63-92BB-488F-1EBB8042F31A">
<createdBy>Katarina</createdBy>
<createdTime>2013-11-17 22:23:30 UTC</createdTime>
<generatorID>DF6E9B81-1B34-77AB-97F6-96E0B7FDF13C</generatorID>
<ownerDesignName>eggshell_model</ownerDesignName>
<nullsAllowed>true</nullsAllowed>
<use>0</use>
<logicalDatatype>LOGDT019</logicalDatatype>
<domain>1C83044F-F4AD-B495-5726-6FF2A6D331C5</domain>
<delegate>07CFB098-C333-416D-D54B-E21C6971A80B</delegate>
<previousColumn>false</previousColumn>
<autoIncrementCycle>false</autoIncrementCycle>
<associations>
<colAssociation fkAssociation="B80040F0-87CA-3FDD-13D7-0EEFCDA4FA44" referredColumn="07CFB098-C333-416D-D54B-E21C6971A80B"/>
</associations>
</Column>
<Column class="oracle.dbtools.crest.model.design.relational.Column" name="contract_id" id="91706CB8-212A-C28C-27D2-4C9AA99D2FF9">
<createdBy>Katarina</createdBy>
<createdTime>2013-11-17 22:23:30 UTC</createdTime>
<generatorID>4624D7F9-96A2-93C7-F526-CE18F6741053</generatorID>
<ownerDesignName>eggshell_model</ownerDesignName>
<use>0</use>
<logicalDatatype>LOGDT019</logicalDatatype>
<domain>1C83044F-F4AD-B495-5726-6FF2A6D331C5</domain>
<delegate>97445B20-2120-1C0C-1F56-B1CDBF96DE2B</delegate>
<previousColumn>false</previousColumn>
<autoIncrementCycle>false</autoIncrementCycle>
<associations>
<colAssociation fkAssociation="D1CC4E48-2F17-E42B-DB5C-3EDBE9731DED" referredColumn="97445B20-2120-1C0C-1F56-B1CDBF96DE2B"/>
</associations>
</Column>
<Column class="oracle.dbtools.crest.model.design.relational.Column" name="mortgage_info" id="F16A1010-E723-1881-B031-AE467388D88B">
<createdBy>Katarina</createdBy>
<createdTime>2013-11-17 22:23:30 UTC</createdTime>
<generatorID>B32E71C1-1DE7-8338-8702-838F7C34B159</generatorID>
<ownerDesignName>eggshell_model</ownerDesignName>
<nullsAllowed>true</nullsAllowed>
<use>0</use>
<logicalDatatype>LOGDT024</logicalDatatype>
<domain>7F21DD7B-81C0-047F-A0FF-9FAFE18CB78F</domain>
<previousColumn>false</previousColumn>
<autoIncrementCycle>false</autoIncrementCycle>
</Column>
<Column class="oracle.dbtools.crest.model.design.relational.Column" name="first_name" id="D79093A6-4C6F-B074-78AA-8A605B593F87">
<createdBy>Katarina</createdBy>
<createdTime>2013-11-17 22:23:30 UTC</createdTime>
<generatorID>CB373D38-B2A5-B575-1A24-85F78AE12CB2</generatorID>
<ownerDesignName>eggshell_model</ownerDesignName>
<use>0</use>
<logicalDatatype>LOGDT024</logicalDatatype>
<domain>86AA045B-36F3-1583-4152-E165A08977B7</domain>
<previousColumn>false</previousColumn>
<autoIncrementCycle>false</autoIncrementCycle>
</Column>
<Column class="oracle.dbtools.crest.model.design.relational.Column" name="last_name" id="9E6EC04B-3E58-61F3-7CB9-C2E9C5C8768B">
<createdBy>Katarina</createdBy>
<createdTime>2013-11-17 22:23:30 UTC</createdTime>
<generatorID>71B53118-E74F-AE08-9D18-6BF07771D96F</generatorID>
<ownerDesignName>eggshell_model</ownerDesignName>
<use>0</use>
<logicalDatatype>LOGDT024</logicalDatatype>
<domain>86AA045B-36F3-1583-4152-E165A08977B7</domain>
<previousColumn>false</previousColumn>
<autoIncrementCycle>false</autoIncrementCycle>
</Column>
<Column class="oracle.dbtools.crest.model.design.relational.Column" name="phone_number" id="9330F78F-ED1E-8BEC-0294-554C975B91DA">
<createdBy>Katarina</createdBy>
<createdTime>2013-11-17 22:23:30 UTC</createdTime>
<generatorID>B1F7A6D1-CBDF-B975-A932-1F45D5C38025</generatorID>
<ownerDesignName>eggshell_model</ownerDesignName>
<use>0</use>
<logicalDatatype>LOGDT024</logicalDatatype>
<domain>40E07E34-97A2-BAF2-36CF-C6FC09EE1E1E</domain>
<previousColumn>false</previousColumn>
<autoIncrementCycle>false</autoIncrementCycle>
</Column>
</columns>
<indexes>
<ind_PK_UK class="oracle.dbtools.crest.model.design.relational.Index" id="157D6CB4-30C8-8F6D-8652-EE86671B2A7C" name="Customer_PK">
<createdBy>Katarina</createdBy>
<createdTime>2013-11-17 22:23:30 UTC</createdTime>
<generatorID>65CC6DC3-88D4-1CD2-38F4-3CFFA636592A</generatorID>
<ownerDesignName>eggshell_model</ownerDesignName>
<pk>true</pk>
<indexState>Primary Constraint</indexState>
<indexColumnUsage>
<colUsage columnID="B4BBD36B-3BA2-35BC-37F2-BC65DE6134F5"/>
</indexColumnUsage>
</ind_PK_UK>
<ind_PK_UK class="oracle.dbtools.crest.model.design.relational.Index" id="E63AE751-BE16-F972-3632-47441E29956D" name="Customer_contract_rel">
<createdBy>Katarina</createdBy>
<createdTime>2013-11-17 22:23:30 UTC</createdTime>
<generatorID>F1016D1C-24B5-032C-669D-BC52D3DFD37E</generatorID>
<ownerDesignName>eggshell_model</ownerDesignName>
<indexState>Foreign Key</indexState>
<indexColumnUsage>
<colUsage columnID="91706CB8-212A-C28C-27D2-4C9AA99D2FF9"/>
</indexColumnUsage>
</ind_PK_UK>
<ind_PK_UK class="oracle.dbtools.crest.model.design.relational.Index" id="07839C04-94F7-5963-0D87-29D3E1F5FA27" name="customer_user">
<createdBy>Katarina</createdBy>
<createdTime>2013-11-17 22:23:30 UTC</createdTime>
<generatorID>5C95BED3-819F-738E-7DEF-69DBF9B852AE</generatorID>
<ownerDesignName>eggshell_model</ownerDesignName>
<indexState>Foreign Key</indexState>
<indexColumnUsage>
<colUsage columnID="9B71CDB1-4B63-92BB-488F-1EBB8042F31A"/>
</indexColumnUsage>
</ind_PK_UK>
</indexes>
</Table>